[
  [
    0,
    null
  ],
  [
    1,
    {
      "json_class": "RPG::Enemy",
      "name": {
        "json_class": "TranslatableString",
        "original   ": "スライム",
        "translation": "Slime"
      },
      "note": {
        "json_class": "TranslatableString",
        "original   ": "",
        "translation": ""
      }
    }
  ],
  [
    2,
    {
      "json_class": "RPG::Enemy",
      "name": {
        "json_class": "TranslatableString",
        "original   ": "こうもり",
        "translation": ""
      },
      "note": {
        "json_class": "TranslatableString",
        "original   ": "",
        "translation": ""
      }
    }
  ],
  [
    3,
    {
      "json_class": "RPG::Enemy",
      "name": {
        "json_class": "TranslatableString",
        "original   ": "ホーネット",
        "translation": "ーNet"
      },
      "note": {
        "json_class": "TranslatableString",
        "original   ": "",
        "translation": ""
      }
    }
  ],
  [
    4,
    {
      "json_class": "RPG::Enemy",
      "name": {
        "json_class": "TranslatableString",
        "original   ": "大グモ",
        "translation": "Great spider"
      },
      "note": {
        "json_class": "TranslatableString",
        "original   ": "",
        "translation": ""
      }
    }
  ],
  [
    5,
    {
      "json_class": "RPG::Enemy",
      "name": {
        "json_class": "TranslatableString",
        "original   ": "大ネズミ",
        "translation": "Large rat"
      },
      "note": {
        "json_class": "TranslatableString",
        "original   ": "",
        "translation": ""
      }
    }
  ],
  [
    6,
    {
      "json_class": "RPG::Enemy",
      "name": {
        "json_class": "TranslatableString",
        "original   ": "ウィスプ",
        "translation": "Wisp"
      },
      "note": {
        "json_class": "TranslatableString",
        "original   ": "",
        "translation": ""
      }
    }
  ],
  [
    7,
    {
      "json_class": "RPG::Enemy",
      "name": {
        "json_class": "TranslatableString",
        "original   ": "大蛇",
        "translation": "Serpent"
      },
      "note": {
        "json_class": "TranslatableString",
        "original   ": "",
        "translation": ""
      }
    }
  ],
  [
    8,
    {
      "json_class": "RPG::Enemy",
      "name": {
        "json_class": "TranslatableString",
        "original   ": "大サソリ",
        "translation": "Large scorpion"
      },
      "note": {
        "json_class": "TranslatableString",
        "original   ": "",
        "translation": ""
      }
    }
  ],
  [
    9,
    {
      "json_class": "RPG::Enemy",
      "name": {
        "json_class": "TranslatableString",
        "original   ": "大クラゲ",
        "translation": "Large jellyfish"
      },
      "note": {
        "json_class": "TranslatableString",
        "original   ": "",
        "translation": ""
      }
    }
  ],
  [
    10,
    {
      "json_class": "RPG::Enemy",
      "name": {
        "json_class": "TranslatableString",
        "original   ": "食人花",
        "translation": "Food flowers"
      },
      "note": {
        "json_class": "TranslatableString",
        "original   ": "",
        "translation": ""
      }
    }
  ],
  [
    11,
    {
      "json_class": "RPG::Enemy",
      "name": {
        "json_class": "TranslatableString",
        "original   ": "ゴースト",
        "translation": "ーA strike"
      },
      "note": {
        "json_class": "TranslatableString",
        "original   ": "",
        "translation": ""
      }
    }
  ],
  [
    12,
    {
      "json_class": "RPG::Enemy",
      "name": {
        "json_class": "TranslatableString",
        "original   ": "スケルトン",
        "translation": "Skeleton"
      },
      "note": {
        "json_class": "TranslatableString",
        "original   ": "",
        "translation": ""
      }
    }
  ],
  [
    13,
    {
      "json_class": "RPG::Enemy",
      "name": {
        "json_class": "TranslatableString",
        "original   ": "オーク",
        "translation": "ー"
      },
      "note": {
        "json_class": "TranslatableString",
        "original   ": "",
        "translation": ""
      }
    }
  ],
  [
    14,
    {
      "json_class": "RPG::Enemy",
      "name": {
        "json_class": "TranslatableString",
        "original   ": "インプ",
        "translation": "Imp"
      },
      "note": {
        "json_class": "TranslatableString",
        "original   ": "",
        "translation": ""
      }
    }
  ],
  [
    15,
    {
      "json_class": "RPG::Enemy",
      "name": {
        "json_class": "TranslatableString",
        "original   ": "ゲイザー",
        "translation": "Geyserー"
      },
      "note": {
        "json_class": "TranslatableString",
        "original   ": "",
        "translation": ""
      }
    }
  ],
  [
    16,
    {
      "json_class": "RPG::Enemy",
      "name": {
        "json_class": "TranslatableString",
        "original   ": "パペット",
        "translation": "Puppet"
      },
      "note": {
        "json_class": "TranslatableString",
        "original   ": "",
        "translation": ""
      }
    }
  ],
  [
    17,
    {
      "json_class": "RPG::Enemy",
      "name": {
        "json_class": "TranslatableString",
        "original   ": "ゾンビ",
        "translation": "Zombie"
      },
      "note": {
        "json_class": "TranslatableString",
        "original   ": "",
        "translation": ""
      }
    }
  ],
  [
    18,
    {
      "json_class": "RPG::Enemy",
      "name": {
        "json_class": "TranslatableString",
        "original   ": "コカトリス",
        "translation": "Cocatris"
      },
      "note": {
        "json_class": "TranslatableString",
        "original   ": "",
        "translation": ""
      }
    }
  ],
  [
    19,
    {
      "json_class": "RPG::Enemy",
      "name": {
        "json_class": "TranslatableString",
        "original   ": "キマイラ",
        "translation": "Chimaera"
      },
      "note": {
        "json_class": "TranslatableString",
        "original   ": "",
        "translation": ""
      }
    }
  ],
  [
    20,
    {
      "json_class": "RPG::Enemy",
      "name": {
        "json_class": "TranslatableString",
        "original   ": "ミミック",
        "translation": "Mimic"
      },
      "note": {
        "json_class": "TranslatableString",
        "original   ": "",
        "translation": ""
      }
    }
  ],
  [
    21,
    {
      "json_class": "RPG::Enemy",
      "name": {
        "json_class": "TranslatableString",
        "original   ": "ウェアウルフ",
        "translation": "Werewolf"
      },
      "note": {
        "json_class": "TranslatableString",
        "original   ": "",
        "translation": ""
      }
    }
  ],
  [
    22,
    {
      "json_class": "RPG::Enemy",
      "name": {
        "json_class": "TranslatableString",
        "original   ": "サハギン",
        "translation": "Sahagin"
      },
      "note": {
        "json_class": "TranslatableString",
        "original   ": "",
        "translation": ""
      }
    }
  ],
  [
    23,
    {
      "json_class": "RPG::Enemy",
      "name": {
        "json_class": "TranslatableString",
        "original   ": "オーガ",
        "translation": "ー"
      },
      "note": {
        "json_class": "TranslatableString",
        "original   ": "",
        "translation": ""
      }
    }
  ],
  [
    24,
    {
      "json_class": "RPG::Enemy",
      "name": {
        "json_class": "TranslatableString",
        "original   ": "ガーゴイル",
        "translation": "ーGoil"
      },
      "note": {
        "json_class": "TranslatableString",
        "original   ": "",
        "translation": ""
      }
    }
  ],
  [
    25,
    {
      "json_class": "RPG::Enemy",
      "name": {
        "json_class": "TranslatableString",
        "original   ": "ラミア",
        "translation": "Lamia"
      },
      "note": {
        "json_class": "TranslatableString",
        "original   ": "",
        "translation": ""
      }
    }
  ],
  [
    26,
    {
      "json_class": "RPG::Enemy",
      "name": {
        "json_class": "TranslatableString",
        "original   ": "ヴァンパイア",
        "translation": "Vampire"
      },
      "note": {
        "json_class": "TranslatableString",
        "original   ": "",
        "translation": ""
      }
    }
  ],
  [
    27,
    {
      "json_class": "RPG::Enemy",
      "name": {
        "json_class": "TranslatableString",
        "original   ": "サキュバス",
        "translation": "Succubus"
      },
      "note": {
        "json_class": "TranslatableString",
        "original   ": "",
        "translation": ""
      }
    }
  ],
  [
    28,
    {
      "json_class": "RPG::Enemy",
      "name": {
        "json_class": "TranslatableString",
        "original   ": "デーモン",
        "translation": "ー"
      },
      "note": {
        "json_class": "TranslatableString",
        "original   ": "",
        "translation": ""
      }
    }
  ],
  [
    29,
    {
      "json_class": "RPG::Enemy",
      "name": {
        "json_class": "TranslatableString",
        "original   ": "魔王",
        "translation": "Devil"
      },
      "note": {
        "json_class": "TranslatableString",
        "original   ": "",
        "translation": ""
      }
    }
  ],
  [
    30,
    {
      "json_class": "RPG::Enemy",
      "name": {
        "json_class": "TranslatableString",
        "original   ": "魔神",
        "translation": "Devil"
      },
      "note": {
        "json_class": "TranslatableString",
        "original   ": "",
        "translation": ""
      }
    }
  ],
  [
    31,
    {
      "json_class": "RPG::Enemy",
      "name": {
        "json_class": "TranslatableString",
        "original   ": "",
        "translation": ""
      },
      "note": {
        "json_class": "TranslatableString",
        "original   ": "",
        "translation": ""
      }
    }
  ],
  [
    32,
    {
      "json_class": "RPG::Enemy",
      "name": {
        "json_class": "TranslatableString",
        "original   ": "",
        "translation": ""
      },
      "note": {
        "json_class": "TranslatableString",
        "original   ": "",
        "translation": ""
      }
    }
  ],
  [
    33,
    {
      "json_class": "RPG::Enemy",
      "name": {
        "json_class": "TranslatableString",
        "original   ": "",
        "translation": ""
      },
      "note": {
        "json_class": "TranslatableString",
        "original   ": "",
        "translation": ""
      }
    }
  ],
  [
    34,
    {
      "json_class": "RPG::Enemy",
      "name": {
        "json_class": "TranslatableString",
        "original   ": "",
        "translation": ""
      },
      "note": {
        "json_class": "TranslatableString",
        "original   ": "",
        "translation": ""
      }
    }
  ],
  [
    35,
    {
      "json_class": "RPG::Enemy",
      "name": {
        "json_class": "TranslatableString",
        "original   ": "",
        "translation": ""
      },
      "note": {
        "json_class": "TranslatableString",
        "original   ": "",
        "translation": ""
      }
    }
  ],
  [
    36,
    {
      "json_class": "RPG::Enemy",
      "name": {
        "json_class": "TranslatableString",
        "original   ": "",
        "translation": ""
      },
      "note": {
        "json_class": "TranslatableString",
        "original   ": "",
        "translation": ""
      }
    }
  ],
  [
    37,
    {
      "json_class": "RPG::Enemy",
      "name": {
        "json_class": "TranslatableString",
        "original   ": "",
        "translation": ""
      },
      "note": {
        "json_class": "TranslatableString",
        "original   ": "",
        "translation": ""
      }
    }
  ],
  [
    38,
    {
      "json_class": "RPG::Enemy",
      "name": {
        "json_class": "TranslatableString",
        "original   ": "",
        "translation": ""
      },
      "note": {
        "json_class": "TranslatableString",
        "original   ": "",
        "translation": ""
      }
    }
  ],
  [
    39,
    {
      "json_class": "RPG::Enemy",
      "name": {
        "json_class": "TranslatableString",
        "original   ": "",
        "translation": ""
      },
      "note": {
        "json_class": "TranslatableString",
        "original   ": "",
        "translation": ""
      }
    }
  ],
  [
    40,
    {
      "json_class": "RPG::Enemy",
      "name": {
        "json_class": "TranslatableString",
        "original   ": "",
        "translation": ""
      },
      "note": {
        "json_class": "TranslatableString",
        "original   ": "",
        "translation": ""
      }
    }
  ],
  [
    41,
    {
      "json_class": "RPG::Enemy",
      "name": {
        "json_class": "TranslatableString",
        "original   ": "",
        "translation": ""
      },
      "note": {
        "json_class": "TranslatableString",
        "original   ": "",
        "translation": ""
      }
    }
  ],
  [
    42,
    {
      "json_class": "RPG::Enemy",
      "name": {
        "json_class": "TranslatableString",
        "original   ": "",
        "translation": ""
      },
      "note": {
        "json_class": "TranslatableString",
        "original   ": "",
        "translation": ""
      }
    }
  ],
  [
    43,
    {
      "json_class": "RPG::Enemy",
      "name": {
        "json_class": "TranslatableString",
        "original   ": "",
        "translation": ""
      },
      "note": {
        "json_class": "TranslatableString",
        "original   ": "",
        "translation": ""
      }
    }
  ],
  [
    44,
    {
      "json_class": "RPG::Enemy",
      "name": {
        "json_class": "TranslatableString",
        "original   ": "",
        "translation": ""
      },
      "note": {
        "json_class": "TranslatableString",
        "original   ": "",
        "translation": ""
      }
    }
  ],
  [
    45,
    {
      "json_class": "RPG::Enemy",
      "name": {
        "json_class": "TranslatableString",
        "original   ": "",
        "translation": ""
      },
      "note": {
        "json_class": "TranslatableString",
        "original   ": "",
        "translation": ""
      }
    }
  ],
  [
    46,
    {
      "json_class": "RPG::Enemy",
      "name": {
        "json_class": "TranslatableString",
        "original   ": "",
        "translation": ""
      },
      "note": {
        "json_class": "TranslatableString",
        "original   ": "",
        "translation": ""
      }
    }
  ],
  [
    47,
    {
      "json_class": "RPG::Enemy",
      "name": {
        "json_class": "TranslatableString",
        "original   ": "",
        "translation": ""
      },
      "note": {
        "json_class": "TranslatableString",
        "original   ": "",
        "translation": ""
      }
    }
  ],
  [
    48,
    {
      "json_class": "RPG::Enemy",
      "name": {
        "json_class": "TranslatableString",
        "original   ": "",
        "translation": ""
      },
      "note": {
        "json_class": "TranslatableString",
        "original   ": "",
        "translation": ""
      }
    }
  ],
  [
    49,
    {
      "json_class": "RPG::Enemy",
      "name": {
        "json_class": "TranslatableString",
        "original   ": "",
        "translation": ""
      },
      "note": {
        "json_class": "TranslatableString",
        "original   ": "",
        "translation": ""
      }
    }
  ],
  [
    50,
    {
      "json_class": "RPG::Enemy",
      "name": {
        "json_class": "TranslatableString",
        "original   ": "",
        "translation": ""
      },
      "note": {
        "json_class": "TranslatableString",
        "original   ": "",
        "translation": ""
      }
    }
  ],
  [
    51,
    {
      "json_class": "RPG::Enemy",
      "name": {
        "json_class": "TranslatableString",
        "original   ": "",
        "translation": ""
      },
      "note": {
        "json_class": "TranslatableString",
        "original   ": "",
        "translation": ""
      }
    }
  ],
  [
    52,
    {
      "json_class": "RPG::Enemy",
      "name": {
        "json_class": "TranslatableString",
        "original   ": "",
        "translation": ""
      },
      "note": {
        "json_class": "TranslatableString",
        "original   ": "",
        "translation": ""
      }
    }
  ],
  [
    53,
    {
      "json_class": "RPG::Enemy",
      "name": {
        "json_class": "TranslatableString",
        "original   ": "",
        "translation": ""
      },
      "note": {
        "json_class": "TranslatableString",
        "original   ": "",
        "translation": ""
      }
    }
  ],
  [
    54,
    {
      "json_class": "RPG::Enemy",
      "name": {
        "json_class": "TranslatableString",
        "original   ": "",
        "translation": ""
      },
      "note": {
        "json_class": "TranslatableString",
        "original   ": "",
        "translation": ""
      }
    }
  ],
  [
    55,
    {
      "json_class": "RPG::Enemy",
      "name": {
        "json_class": "TranslatableString",
        "original   ": "",
        "translation": ""
      },
      "note": {
        "json_class": "TranslatableString",
        "original   ": "",
        "translation": ""
      }
    }
  ],
  [
    56,
    {
      "json_class": "RPG::Enemy",
      "name": {
        "json_class": "TranslatableString",
        "original   ": "",
        "translation": ""
      },
      "note": {
        "json_class": "TranslatableString",
        "original   ": "",
        "translation": ""
      }
    }
  ],
  [
    57,
    {
      "json_class": "RPG::Enemy",
      "name": {
        "json_class": "TranslatableString",
        "original   ": "",
        "translation": ""
      },
      "note": {
        "json_class": "TranslatableString",
        "original   ": "",
        "translation": ""
      }
    }
  ],
  [
    58,
    {
      "json_class": "RPG::Enemy",
      "name": {
        "json_class": "TranslatableString",
        "original   ": "",
        "translation": ""
      },
      "note": {
        "json_class": "TranslatableString",
        "original   ": "",
        "translation": ""
      }
    }
  ],
  [
    59,
    {
      "json_class": "RPG::Enemy",
      "name": {
        "json_class": "TranslatableString",
        "original   ": "",
        "translation": ""
      },
      "note": {
        "json_class": "TranslatableString",
        "original   ": "",
        "translation": ""
      }
    }
  ],
  [
    60,
    {
      "json_class": "RPG::Enemy",
      "name": {
        "json_class": "TranslatableString",
        "original   ": "",
        "translation": ""
      },
      "note": {
        "json_class": "TranslatableString",
        "original   ": "",
        "translation": ""
      }
    }
  ],
  [
    61,
    {
      "json_class": "RPG::Enemy",
      "name": {
        "json_class": "TranslatableString",
        "original   ": "",
        "translation": ""
      },
      "note": {
        "json_class": "TranslatableString",
        "original   ": "",
        "translation": ""
      }
    }
  ],
  [
    62,
    {
      "json_class": "RPG::Enemy",
      "name": {
        "json_class": "TranslatableString",
        "original   ": "",
        "translation": ""
      },
      "note": {
        "json_class": "TranslatableString",
        "original   ": "",
        "translation": ""
      }
    }
  ],
  [
    63,
    {
      "json_class": "RPG::Enemy",
      "name": {
        "json_class": "TranslatableString",
        "original   ": "",
        "translation": ""
      },
      "note": {
        "json_class": "TranslatableString",
        "original   ": "",
        "translation": ""
      }
    }
  ],
  [
    64,
    {
      "json_class": "RPG::Enemy",
      "name": {
        "json_class": "TranslatableString",
        "original   ": "",
        "translation": ""
      },
      "note": {
        "json_class": "TranslatableString",
        "original   ": "",
        "translation": ""
      }
    }
  ],
  [
    65,
    {
      "json_class": "RPG::Enemy",
      "name": {
        "json_class": "TranslatableString",
        "original   ": "",
        "translation": ""
      },
      "note": {
        "json_class": "TranslatableString",
        "original   ": "",
        "translation": ""
      }
    }
  ],
  [
    66,
    {
      "json_class": "RPG::Enemy",
      "name": {
        "json_class": "TranslatableString",
        "original   ": "",
        "translation": ""
      },
      "note": {
        "json_class": "TranslatableString",
        "original   ": "",
        "translation": ""
      }
    }
  ],
  [
    67,
    {
      "json_class": "RPG::Enemy",
      "name": {
        "json_class": "TranslatableString",
        "original   ": "",
        "translation": ""
      },
      "note": {
        "json_class": "TranslatableString",
        "original   ": "",
        "translation": ""
      }
    }
  ],
  [
    68,
    {
      "json_class": "RPG::Enemy",
      "name": {
        "json_class": "TranslatableString",
        "original   ": "",
        "translation": ""
      },
      "note": {
        "json_class": "TranslatableString",
        "original   ": "",
        "translation": ""
      }
    }
  ],
  [
    69,
    {
      "json_class": "RPG::Enemy",
      "name": {
        "json_class": "TranslatableString",
        "original   ": "",
        "translation": ""
      },
      "note": {
        "json_class": "TranslatableString",
        "original   ": "",
        "translation": ""
      }
    }
  ],
  [
    70,
    {
      "json_class": "RPG::Enemy",
      "name": {
        "json_class": "TranslatableString",
        "original   ": "",
        "translation": ""
      },
      "note": {
        "json_class": "TranslatableString",
        "original   ": "",
        "translation": ""
      }
    }
  ],
  [
    71,
    {
      "json_class": "RPG::Enemy",
      "name": {
        "json_class": "TranslatableString",
        "original   ": "シャフィアンシス",
        "translation": "Shafi Ansys"
      },
      "note": {
        "json_class": "TranslatableString",
        "original   ": "",
        "translation": ""
      }
    }
  ],
  [
    72,
    {
      "json_class": "RPG::Enemy",
      "name": {
        "json_class": "TranslatableString",
        "original   ": "",
        "translation": ""
      },
      "note": {
        "json_class": "TranslatableString",
        "original   ": "",
        "translation": ""
      }
    }
  ],
  [
    73,
    {
      "json_class": "RPG::Enemy",
      "name": {
        "json_class": "TranslatableString",
        "original   ": "",
        "translation": ""
      },
      "note": {
        "json_class": "TranslatableString",
        "original   ": "",
        "translation": ""
      }
    }
  ],
  [
    74,
    {
      "json_class": "RPG::Enemy",
      "name": {
        "json_class": "TranslatableString",
        "original   ": "",
        "translation": ""
      },
      "note": {
        "json_class": "TranslatableString",
        "original   ": "",
        "translation": ""
      }
    }
  ],
  [
    75,
    {
      "json_class": "RPG::Enemy",
      "name": {
        "json_class": "TranslatableString",
        "original   ": "",
        "translation": ""
      },
      "note": {
        "json_class": "TranslatableString",
        "original   ": "",
        "translation": ""
      }
    }
  ],
  [
    76,
    {
      "json_class": "RPG::Enemy",
      "name": {
        "json_class": "TranslatableString",
        "original   ": "",
        "translation": ""
      },
      "note": {
        "json_class": "TranslatableString",
        "original   ": "",
        "translation": ""
      }
    }
  ],
  [
    77,
    {
      "json_class": "RPG::Enemy",
      "name": {
        "json_class": "TranslatableString",
        "original   ": "",
        "translation": ""
      },
      "note": {
        "json_class": "TranslatableString",
        "original   ": "",
        "translation": ""
      }
    }
  ],
  [
    78,
    {
      "json_class": "RPG::Enemy",
      "name": {
        "json_class": "TranslatableString",
        "original   ": "",
        "translation": ""
      },
      "note": {
        "json_class": "TranslatableString",
        "original   ": "",
        "translation": ""
      }
    }
  ],
  [
    79,
    {
      "json_class": "RPG::Enemy",
      "name": {
        "json_class": "TranslatableString",
        "original   ": "",
        "translation": ""
      },
      "note": {
        "json_class": "TranslatableString",
        "original   ": "",
        "translation": ""
      }
    }
  ],
  [
    80,
    {
      "json_class": "RPG::Enemy",
      "name": {
        "json_class": "TranslatableString",
        "original   ": "",
        "translation": ""
      },
      "note": {
        "json_class": "TranslatableString",
        "original   ": "",
        "translation": ""
      }
    }
  ]
]